zdppy_fastapi/__init__.py
zdppy_fastapi/exceptions.py
zdppy_fastapi/fastapi.py
zdppy_fastapi/utils.py
zdppy_fastapi-0.1.0.dist-info/LICENSE
zdppy_fastapi-0.1.0.dist-info/WHEEL
zdppy_fastapi-0.1.0.dist-info/METADATA
zdppy_fastapi-0.1.0.dist-info/RECORD
